itip/__init__.py
itip/version.py
itip-0.0.0.dist-info/METADATA
itip-0.0.0.dist-info/WHEEL
itip-0.0.0.dist-info/top_level.txt
itip-0.0.0.dist-info/RECORD
