Metadata-Version: 2.1
Name: itip
Version: 0.0.0
Summary: itip
Home-page: http://github.com/zhiqingxiao/itip/
Author: Zhiqing Xiao
Author-email: xzq.xiaozhiqing@gmail.com
License: UNKNOWN
Platform: UNKNOWN
Classifier: Programming Language :: Python
Classifier: Intended Audience :: Science/Research
